iatp/__init__.py
iatp/attestation.py
iatp/cli.py
iatp/hf_utils.py
iatp/ipc_pipes.py
iatp/main.py
iatp/policy_engine.py
iatp/py.typed
iatp/recovery.py
iatp/models/__init__.py
iatp/security/__init__.py
iatp/sidecar/__init__.py
iatp/telemetry/__init__.py
inter_agent_trust_protocol-0.5.0.dist-info/METADATA
inter_agent_trust_protocol-0.5.0.dist-info/WHEEL
inter_agent_trust_protocol-0.5.0.dist-info/entry_points.txt
inter_agent_trust_protocol-0.5.0.dist-info/top_level.txt
inter_agent_trust_protocol-0.5.0.dist-info/RECORD
