Metadata-Version: 2.4
Name: inter-agent-trust-protocol
Version: 0.5.0
Summary: Inter-Agent Trust Protocol (IATP) - The Envoy for AI Agents. A sidecar architecture with typed IPC pipes for preventing cascading hallucinations in autonomous agent networks.
Home-page: https://github.com/imran-siddique/inter-agent-trust-protocol
Author: Imran Siddique
Author-email: Imran Siddique <imran@example.com>
Maintainer-email: Imran Siddique <imran@example.com>
License: MIT
Project-URL: Homepage, https://github.com/imran-siddique/inter-agent-trust-protocol
Project-URL: Documentation, https://github.com/imran-siddique/inter-agent-trust-protocol#readme
Project-URL: Repository, https://github.com/imran-siddique/inter-agent-trust-protocol.git
Project-URL: Issues, https://github.com/imran-siddique/inter-agent-trust-protocol/issues
Project-URL: Changelog, https://github.com/imran-siddique/inter-agent-trust-protocol/blob/main/CHANGELOG.md
Keywords: agent,ai,llm,trust,security,sidecar,mesh,governance,policy,hallucination,multi-agent,protocol
Classifier: Development Status :: 4 - Beta
Classifier: Intended Audience :: Developers
Classifier: Intended Audience :: Science/Research
Classifier: Topic :: Software Development :: Libraries :: Python Modules
Classifier: Topic :: System :: Distributed Computing
Classifier: Topic :: Security
Classifier: Topic :: Scientific/Engineering :: Artificial Intelligence
Classifier: License :: OSI Approved :: MIT License
Classifier: Programming Language :: Python :: 3
Classifier: Programming Language :: Python :: 3.8
Classifier: Programming Language :: Python :: 3.9
Classifier: Programming Language :: Python :: 3.10
Classifier: Programming Language :: Python :: 3.11
Classifier: Programming Language :: Python :: 3.12
Classifier: Operating System :: OS Independent
Classifier: Typing :: Typed
Requires-Python: >=3.8
Requires-Dist: fastapi>=0.109.1
Requires-Dist: uvicorn>=0.27.0
Requires-Dist: pydantic>=2.5.3
Requires-Dist: httpx>=0.26.0
Requires-Dist: python-dateutil>=2.8.2
Requires-Dist: agent-primitives>=0.1.0
Requires-Dist: click>=8.0.0
Provides-Extra: dev
Requires-Dist: pytest>=7.4.0; extra == "dev"
Requires-Dist: pytest-asyncio>=0.21.0; extra == "dev"
Requires-Dist: pytest-cov>=4.1.0; extra == "dev"
Requires-Dist: mypy>=1.8.0; extra == "dev"
Requires-Dist: ruff>=0.1.0; extra == "dev"
Requires-Dist: pre-commit>=3.6.0; extra == "dev"
Provides-Extra: docs
Requires-Dist: mkdocs>=1.5.0; extra == "docs"
Requires-Dist: mkdocs-material>=9.5.0; extra == "docs"
Requires-Dist: mkdocstrings[python]>=0.24.0; extra == "docs"
Provides-Extra: hf
Requires-Dist: huggingface-hub>=0.20.0; extra == "hf"
Requires-Dist: datasets>=2.16.0; extra == "hf"
Provides-Extra: all
Requires-Dist: inter-agent-trust-protocol[dev,docs,hf]; extra == "all"
Dynamic: author
Dynamic: home-page
Dynamic: requires-python
